yt_dlp_progress/__init__.py
yt_dlp_progress-0.0.4.dist-info/METADATA
yt_dlp_progress-0.0.4.dist-info/WHEEL
yt_dlp_progress-0.0.4.dist-info/entry_points.txt
yt_dlp_progress-0.0.4.dist-info/licenses/LICENSE
yt_dlp_progress-0.0.4.dist-info/RECORD
